{
  "productId": "mouse-redragon-cobra-m711-cobra-m711",
  "category": "mouse",
  "identityLock": {
    "brand": "Redragon",
    "model": "Cobra M711",
    "variant": "Cobra M711"
  },
  "seedUrls": [],
  "anchors": {},
  "requirements": {
    "requiredFields": []
  },
  "seed": {
    "source": "excel",
    "workbook_path": "C:\\Users\\Chris\\Desktop\\spec-harvester - 2\\helper_files\\mouse\\mouseData.xlsm",
    "sheet": "dataEntry",
    "source_column": "FA",
    "source_type": "user_helper_seed",
    "captured_at": "2026-02-11T08:09:56.109Z"
  }
}
