{
  "productId": "mouse-g-wolves-hts-ultra-8k-wireless-hts",
  "category": "mouse",
  "identityLock": {
    "brand": "G-Wolves",
    "model": "HTS Ultra 8K Wireless",
    "variant": "HTS"
  },
  "seedUrls": [],
  "anchors": {},
  "requirements": {
    "requiredFields": []
  },
  "seed": {
    "source": "excel",
    "workbook_path": "C:\\Users\\Chris\\Desktop\\spec-harvester - 2\\helper_files\\mouse\\mouseData.xlsm",
    "sheet": "dataEntry",
    "source_column": "HQ",
    "source_type": "user_helper_seed",
    "captured_at": "2026-02-11T08:09:56.626Z"
  }
}
