{
  "productId": "mouse-logitech-g-pro-x-superlight-2c-pro-x",
  "category": "mouse",
  "identityLock": {
    "brand": "Logitech G",
    "model": "Pro X Superlight 2c",
    "variant": "Pro X"
  },
  "seedUrls": [],
  "anchors": {},
  "requirements": {
    "requiredFields": []
  },
  "seed": {
    "source": "excel",
    "workbook_path": "C:\\Users\\Chris\\Desktop\\spec-harvester - 2\\helper_files\\mouse\\mouseData.xlsm",
    "sheet": "dataEntry",
    "source_column": "DB",
    "source_type": "user_helper_seed",
    "captured_at": "2026-02-11T08:09:55.749Z"
  }
}
